{
"autoplayBgm":false,"autoplayBgs":false,"battleback1Name":"","battleback2Name":"","bgm":{"name":"","pan":0,"pitch":100,"volume":90},"bgs":{"name":"","pan":0,"pitch":100,"volume":90},"disableDashing":false,"displayName":"詛咒之塔","encounterList":[],"encounterStep":30,"height":8,"note":"","parallaxLoopX":false,"parallaxLoopY":false,"parallaxName":"","parallaxShow":true,"parallaxSx":0,"parallaxSy":0,"scrollType":0,"specifyBattleback":false,"tilesetId":4,"width":12,
"data":[7016,7379,7378,7378,7378,7378,7378,7378,7378,7378,7382,7008,7016,7385,7384,7384,7384,7384,7384,7384,7384,7384,7388,7008,7016,4146,4132,4132,4132,4132,4132,4132,4132,4132,4148,7008,7016,4128,4112,4112,4112,4112,4112,4112,4112,4112,4136,7008,7016,4128,4112,4112,4112,4112,4112,4112,4112,4112,4136,7008,7016,4152,4140,4124,4140,4140,4140,4140,4140,4140,4150,7008,7022,7025,7037,4156,7035,7025,7025,7025,7025,7025,7025,7021,7387,7386,7390,1536,7387,7386,7386,7386,7386,7386,7386,7390,0,0,0,0,0,0,0,0,0,0,0,0,0,0,0,0,0,0,0,0,0,0,0,0,0,0,0,0,0,0,0,0,0,0,0,0,0,0,0,0,0,0,0,0,0,0,0,0,0,0,0,0,0,0,0,0,0,0,0,0,0,0,0,0,0,0,0,0,0,0,0,0,0,0,0,0,0,0,0,0,0,0,0,0,0,0,0,0,0,0,0,0,0,0,0,0,0,0,0,0,421,0,0,421,0,0,0,0,0,0,0,0,429,0,0,429,0,0,503,0,0,0,0,103,0,0,0,0,0,0,0,0,0,0,0,0,0,0,0,0,336,337,338,0,0,0,0,0,0,0,0,0,344,348,346,0,0,0,0,0,0,0,0,0,352,353,354,0,0,0,0,0,0,0,0,0,0,0,0,0,0,0,0,0,0,0,0,0,0,0,0,0,0,423,0,0,423,0,0,423,0,0,423,0,0,431,0,0,431,0,0,431,501,502,431,0,0,0,308,98,0,98,308,0,509,510,511,0,0,0,284,0,63,0,284,0,339,340,341,0,0,0,292,0,0,0,292,0,347,87,349,0,0,239,300,0,0,0,300,0,355,356,357,0,0,0,0,0,0,0,0,0,0,0,0,0,0,0,0,0,0,0,0,0,0,0,0,0,0,0,0,0,0,0,0,0,0,0,0,0,0,0,0,0,0,0,0,0,0,0,0,0,0,5,0,0,0,0,0,0,0,0,0,0,0,5,0,0,0,0,0,0,0,0,0,0,0,5,0,0,0,0,0,0,0,0,0,0,0,5,0,0,0,0,0,0,0,0,0,0,0,0,0,0,0,0,0,0,0,0,0,0,0,0,0,5,0,0,0,0,0,0,0,0,0,0,0,0,0,0,0,0,0,0,0,0,0,0,0,0,0,0,0,0,0,0,0,0,0,0,0,0,0,0,0,0,0,0,0,0,0,0,0,0,0,0,0,0,0,0,0,0,0,0,0,0,0,0,0,0,0,0,0,0,0,0,0,0,0,0,0,0,0,0,0,0,0,0,0,0,0,0,0,0,0,0,0,0,0,0,0,0,0,0,0,0,0,0,0,0],
"events":[
null,
{"id":1,"name":"EV001","note":"","pages":[{"conditions":{"actorId":1,"actorValid":false,"itemId":1,"itemValid":false,"selfSwitchCh":"A","selfSwitchValid":false,"switch1Id":1,"switch1Valid":false,"switch2Id":1,"switch2Valid":false,"variableId":1,"variableValid":false,"variableValue":0},"directionFix":false,"image":{"characterIndex":0,"characterName":"","direction":2,"pattern":0,"tileId":0},"list":[{"code":201,"indent":0,"parameters":[0,5,44,8,0,0]},{"code":0,"indent":0,"parameters":[]}],"moveFrequency":3,"moveRoute":{"list":[{"code":0,"parameters":[]}],"repeat":true,"skippable":false,"wait":false},"moveSpeed":3,"moveType":0,"priorityType":0,"stepAnime":false,"through":false,"trigger":0,"walkAnime":true}],"x":3,"y":6},
{"id":2,"name":"EV002","note":"","pages":[{"conditions":{"actorId":1,"actorValid":false,"itemId":1,"itemValid":false,"selfSwitchCh":"A","selfSwitchValid":false,"switch1Id":1,"switch1Valid":false,"switch2Id":1,"switch2Valid":false,"variableId":1,"variableValid":false,"variableValue":0},"directionFix":false,"image":{"tileId":0,"characterName":"poke2","direction":2,"pattern":0,"characterIndex":6},"list":[{"code":101,"indent":0,"parameters":["poke2",6,0,2]},{"code":401,"indent":0,"parameters":["唉～"]},{"code":101,"indent":0,"parameters":["",0,0,2]},{"code":401,"indent":0,"parameters":["怎麼了鬼斯通？"]},{"code":213,"indent":0,"parameters":[0,1,true]},{"code":101,"indent":0,"parameters":["poke2",6,0,2]},{"code":401,"indent":0,"parameters":["你們怎麼來了？是從外地來的吧？"]},{"code":101,"indent":0,"parameters":["",0,0,2]},{"code":401,"indent":0,"parameters":["我們剛進到這個城鎮，就發現一堆村民圍了過來，發生了什"]},{"code":401,"indent":0,"parameters":["麼事嗎？"]},{"code":101,"indent":0,"parameters":["poke2",6,0,2]},{"code":401,"indent":0,"parameters":["(鬼斯通把最近的事情說了一遍..)"]},{"code":101,"indent":0,"parameters":["",0,0,2]},{"code":401,"indent":0,"parameters":["原來是美術館的老闆被幽靈鎧甲給刺傷了，許多居民們認為這一"]},{"code":401,"indent":0,"parameters":["定是鬼斯通在暗中搞鬼，"]},{"code":101,"indent":0,"parameters":["",0,0,2]},{"code":401,"indent":0,"parameters":["對於館長把他安排在荒山野嶺看守墓園心懷恨意，才暗中使"]},{"code":401,"indent":0,"parameters":["壞的，"]},{"code":101,"indent":0,"parameters":["",0,0,2]},{"code":401,"indent":0,"parameters":["殊不知這個環境才是鬼斯通最喜歡的住所，他最近就準備找"]},{"code":401,"indent":0,"parameters":["機會進化為耿鬼了，不過因為總是獨來獨往，也沒辦法為自"]},{"code":401,"indent":0,"parameters":["己證明什麼，"]},{"code":101,"indent":0,"parameters":["poke2",6,0,2]},{"code":401,"indent":0,"parameters":["如果你們能夠幫我洗刷冤屈,那我就告訴你們前"]},{"code":401,"indent":0,"parameters":["往冰雪城的辦法"]},{"code":123,"indent":0,"parameters":["A",0]},{"code":0,"indent":0,"parameters":[]}],"moveFrequency":3,"moveRoute":{"list":[{"code":0,"parameters":[]}],"repeat":true,"skippable":false,"wait":false},"moveSpeed":3,"moveType":0,"priorityType":1,"stepAnime":true,"through":false,"trigger":0,"walkAnime":true},{"conditions":{"actorId":1,"actorValid":false,"itemId":1,"itemValid":false,"selfSwitchCh":"A","selfSwitchValid":true,"switch1Id":1,"switch1Valid":false,"switch2Id":1,"switch2Valid":false,"variableId":1,"variableValid":false,"variableValue":0},"directionFix":false,"image":{"tileId":0,"characterName":"poke2","direction":2,"pattern":0,"characterIndex":6},"list":[{"code":101,"indent":0,"parameters":["poke2",6,0,2]},{"code":401,"indent":0,"parameters":["如果你們能夠幫我洗刷冤屈,那我就告訴你們前"]},{"code":401,"indent":0,"parameters":["往冰雪城的辦法"]},{"code":0,"indent":0,"parameters":[]}],"moveFrequency":3,"moveRoute":{"list":[{"code":0,"parameters":[]}],"repeat":true,"skippable":false,"wait":false},"moveSpeed":3,"moveType":0,"priorityType":1,"stepAnime":true,"through":false,"trigger":0,"walkAnime":true},{"conditions":{"actorId":1,"actorValid":false,"itemId":1,"itemValid":false,"selfSwitchCh":"A","selfSwitchValid":false,"switch1Id":19,"switch1Valid":true,"switch2Id":1,"switch2Valid":false,"variableId":1,"variableValid":false,"variableValue":0},"directionFix":false,"image":{"tileId":0,"characterName":"poke2","direction":2,"pattern":0,"characterIndex":6},"list":[{"code":101,"indent":0,"parameters":["poke2",6,0,2]},{"code":401,"indent":0,"parameters":["怎麼樣，知道怎麼回事了嗎？"]},{"code":102,"indent":0,"parameters":[["是的","還沒"],1,-1,2,0]},{"code":402,"indent":0,"parameters":[0,"是的"]},{"code":101,"indent":1,"parameters":["poke2",6,0,2]},{"code":401,"indent":1,"parameters":["所以真正的犯人是誰？"]},{"code":103,"indent":1,"parameters":[17,6]},{"code":111,"indent":1,"parameters":[1,17,0,945611,0]},{"code":123,"indent":2,"parameters":["B",0]},{"code":0,"indent":2,"parameters":[]},{"code":412,"indent":1,"parameters":[]},{"code":0,"indent":1,"parameters":[]},{"code":402,"indent":0,"parameters":[1,"還沒"]},{"code":0,"indent":1,"parameters":[]},{"code":404,"indent":0,"parameters":[]},{"code":0,"indent":0,"parameters":[]}],"moveFrequency":3,"moveRoute":{"list":[{"code":0,"parameters":[]}],"repeat":true,"skippable":false,"wait":false},"moveSpeed":3,"moveType":0,"priorityType":1,"stepAnime":true,"through":false,"trigger":0,"walkAnime":true},{"conditions":{"actorId":1,"actorValid":false,"itemId":1,"itemValid":false,"selfSwitchCh":"B","selfSwitchValid":true,"switch1Id":1,"switch1Valid":false,"switch2Id":1,"switch2Valid":false,"variableId":1,"variableValid":false,"variableValue":0},"directionFix":false,"image":{"tileId":0,"characterName":"poke2","direction":2,"pattern":0,"characterIndex":6},"list":[{"code":101,"indent":0,"parameters":["poke2",6,0,2]},{"code":401,"indent":0,"parameters":["\\..\\..沒想到會是他!"]},{"code":101,"indent":0,"parameters":["poke2",6,0,2]},{"code":401,"indent":0,"parameters":["其實我知道，老闆為什麼要賣掉美術館，是因"]},{"code":401,"indent":0,"parameters":["為老闆知道希特需要一筆資金去創業，為了能"]},{"code":401,"indent":0,"parameters":["去支持他"]},{"code":101,"indent":0,"parameters":["poke2",6,0,2]},{"code":401,"indent":0,"parameters":["毅然決然地決定賣掉美術館，為了不想讓兒子"]},{"code":401,"indent":0,"parameters":["愧疚，對外宣稱是為了能提高收益而蓋飯店"]},{"code":101,"indent":0,"parameters":["poke2",6,0,2]},{"code":401,"indent":0,"parameters":["也許，正是這突如其來的決定，讓館長一時之"]},{"code":401,"indent":0,"parameters":["間接受不了吧，這個他們經營了大半輩子的美"]},{"code":401,"indent":0,"parameters":["術館說關就關，"]},{"code":101,"indent":0,"parameters":["poke2",6,0,2]},{"code":401,"indent":0,"parameters":["說到底，老威爾還是很愛自己的孩子阿，就是"]},{"code":401,"indent":0,"parameters":["不知道希特知不知道父親的苦心．"]},{"code":121,"indent":0,"parameters":[20,20,0]},{"code":0,"indent":0,"parameters":[]}],"moveFrequency":3,"moveRoute":{"list":[{"code":0,"parameters":[]}],"repeat":true,"skippable":false,"wait":false},"moveSpeed":3,"moveType":0,"priorityType":1,"stepAnime":true,"through":false,"trigger":0,"walkAnime":true},{"conditions":{"actorId":1,"actorValid":false,"itemId":1,"itemValid":false,"selfSwitchCh":"A","selfSwitchValid":false,"switch1Id":20,"switch1Valid":true,"switch2Id":1,"switch2Valid":false,"variableId":1,"variableValid":false,"variableValue":0},"directionFix":false,"image":{"tileId":0,"characterName":"poke2","direction":2,"pattern":0,"characterIndex":6},"list":[{"code":101,"indent":0,"parameters":["poke2",6,0,2]},{"code":401,"indent":0,"parameters":["只要你拿著這個去到冰雪城前的大樹，他就會"]},{"code":401,"indent":0,"parameters":["把你傳送進去！"]},{"code":101,"indent":0,"parameters":["",0,0,2]},{"code":401,"indent":0,"parameters":["獲得傳送石！"]},{"code":250,"indent":0,"parameters":[{"name":"Item3","volume":90,"pitch":100,"pan":0}]},{"code":126,"indent":0,"parameters":[25,0,0,1]},{"code":123,"indent":0,"parameters":["C",0]},{"code":0,"indent":0,"parameters":[]}],"moveFrequency":3,"moveRoute":{"list":[{"code":0,"parameters":[]}],"repeat":true,"skippable":false,"wait":false},"moveSpeed":3,"moveType":0,"priorityType":1,"stepAnime":true,"through":false,"trigger":0,"walkAnime":true},{"conditions":{"actorId":1,"actorValid":false,"itemId":1,"itemValid":false,"selfSwitchCh":"C","selfSwitchValid":true,"switch1Id":1,"switch1Valid":false,"switch2Id":1,"switch2Valid":false,"variableId":1,"variableValid":false,"variableValue":0},"directionFix":false,"image":{"tileId":0,"characterName":"poke2","direction":2,"pattern":0,"characterIndex":6},"list":[{"code":101,"indent":0,"parameters":["poke2",6,0,2]},{"code":401,"indent":0,"parameters":["祝你好運！最後，給你提一個醒，不要相信智者．"]},{"code":0,"indent":0,"parameters":[]}],"moveFrequency":3,"moveRoute":{"list":[{"code":0,"parameters":[]}],"repeat":true,"skippable":false,"wait":false},"moveSpeed":3,"moveType":0,"priorityType":1,"stepAnime":true,"through":false,"trigger":0,"walkAnime":true}],"x":9,"y":2}
]
}